syngle/__init__.py
syngle/__main__.py
syngle/decorator.py
syngle/metaclass.py
syngle-0.4.1.dist-info/LICENSE
syngle-0.4.1.dist-info/WHEEL
syngle-0.4.1.dist-info/METADATA
syngle-0.4.1.dist-info/RECORD
