Metadata-Version: 2.1
Name: syngle
Version: 0.4.1
Summary: Simple package implementing the Singleton pattern as a metaclass and decorator.
Home-page: https://valentincalomme.github.io/syngle/
License: MIT
Author: Valentin Calomme
Author-email: dev@valentincalomme.com
Requires-Python: >=3.7,<4.0
Classifier: License :: OSI Approved :: MIT License
Classifier: Programming Language :: Python :: 3
Classifier: Programming Language :: Python :: 3.7
Classifier: Programming Language :: Python :: 3.8
Project-URL: Repository, https://github.com/valentincalomme/syngle
